<Properties StartupConfiguration="{CE393D87-F00E-424B-94ED-4B4447FDFB97}|Default">
  <MonoDevelop.Ide.DebuggingService.Breakpoints>
    <BreakpointStore />
  </MonoDevelop.Ide.DebuggingService.Breakpoints>
  <MonoDevelop.Ide.Workspace ActiveConfiguration="Debug" />
  <MonoDevelop.Ide.Workbench>
    <Pads>
      <Pad Id="ProjectPad">
        <State name="__root__">
          <Node name="CodeFlix.Catalog" expanded="True">
            <Node name="src" expanded="True">
              <Node name="CodeFlix.Catalog.Application" expanded="True" />
              <Node name="CodeFlix.Catalog.Domain" expanded="True">
                <Node name="Repository" expanded="True" />
                <Node name="SeedWork" expanded="True" />
              </Node>
            </Node>
            <Node name="tests" expanded="True">
              <Node name="CodeFlix.Catalog.UnitTests" expanded="True">
                <Node name="Application" expanded="True">
                  <Node name="CreateCategory" expanded="True">
                    <Node name="CreateCategoryTest.cs" selected="True" />
                  </Node>
                </Node>
              </Node>
            </Node>
          </Node>
        </State>
      </Pad>
    </Pads>
  </MonoDevelop.Ide.Workbench>
  <MonoDevelop.Ide.DebuggingService.PinnedWatches />
  <MultiItemStartupConfigurations />
  <MonoDevelop.Ide.ItemProperties.tests.CodeFlix.Catalog.UnitTests PreferredExecutionTarget="MonoDevelop.Default" />
  <MonoDevelop.Ide.ItemProperties.src.CodeFlix.Catalog.Domain FirstBuild="True" />
</Properties>